{"pagination":{"next_url":"https:\/\/api.instagram.com\/v1\/users\/203110951\/media\/recent?access_token=203110951.d29b6ba.925b18d2ec2742a882137218575510f0\u0026max_id=382190635795276059_203110951","next_max_id":"382190635795276059_203110951"},"meta":{"code":200},"data":[{"attribution":null,"tags":["wow","snapseed","bestoftheday","photooftheday","jj","statigram","webstagram","picoftheday","best","cool"],"type":"image","location":{"latitude":40.7292082,"longitude":-73.995433},"comments":{"count":2,"data":[{"created_time":"1361561503","text":"Neat","from":{"username":"jwheels45","profile_picture":"http:\/\/images.instagram.com\/profiles\/profile_205606283_75sq_1346468328.jpg","id":"205606283","full_name":"jwheels45"},"id":"397129132826091811"},{"created_time":"1361623603","text":"#cool #wow #webstagram #statigram #jj #snapseed #bestoftheday #best #picoftheday #photooftheday","from":{"username":"pelletized","profile_picture":"http:\/\/images.instagram.com\/profiles\/profile_203110951_75sq_1361336165.jpg","id":"203110951","full_name":"ed w"},"id":"397650061742236167"}]},"filter":"Normal","created_time":"1361550342","link":"http:\/\/instagr.am\/p\/WCjbBoDuPt\/","likes":{"count":34,"data":[{"username":"circa_mcmlxxxi","profile_picture":"http:\/\/images.instagram.com\/profiles\/profile_38380741_75sq_1359762454.jpg","id":"38380741","full_name":"Circa_MCMLXXXI"},{"username":"vincenzd","profile_picture":"http:\/\/images.instagram.com\/profiles\/profile_200282792_75sq_1343512064.jpg","id":"200282792","full_name":"vincenzd"},{"username":"swaggykid_16","profile_picture":"http:\/\/images.instagram.com\/profiles\/profile_55733084_75sq_1361299436.jpg","id":"55733084","full_name":"swaggykid_16"},{"username":"blondie81905","profile_picture":"http:\/\/images.instagram.com\/profiles\/profile_254788843_75sq_1353200412.jpg","id":"254788843","full_name":"Erika Toner"},{"username":"fieldspowerfitness","profile_picture":"http:\/\/images.instagram.com\/profiles\/profile_186495958_75sq_1359409740.jpg","id":"186495958","full_name":"Clinton Fields"},{"username":"alyssas90","profile_picture":"http:\/\/images.instagram.com\/profiles\/profile_185851610_75sq_1340506677.jpg","id":"185851610","full_name":"alyssas90"},{"username":"autumn_lotus","profile_picture":"http:\/\/images.instagram.com\/profiles\/profile_45403675_75sq_1348538762.jpg","id":"45403675","full_name":"autumn_lotus"},{"username":"melnaron","profile_picture":"http:\/\/images.instagram.com\/profiles\/profile_187369980_75sq_1340819804.jpg","id":"187369980","full_name":"Dmitry Gureev"},{"username":"leighb1987","profile_picture":"http:\/\/images.instagram.com\/profiles\/profile_182523482_75sq_1350610287.jpg","id":"182523482","full_name":"\ud83c\udf34\u2600\ud83c\udf37"},{"username":"viniciusbocchi","profile_picture":"http:\/\/images.instagram.com\/profiles\/profile_241144830_75sq_1357616658.jpg","id":"241144830","full_name":"Vinicius Bocchi"}]},"images":{"low_resolution":{"url":"http:\/\/distilleryimage5.s3.amazonaws.com\/8077de707d0c11e2a0d522000a1f970a_6.jpg","width":306,"height":306},"thumbnail":{"url":"http:\/\/distilleryimage5.s3.amazonaws.com\/8077de707d0c11e2a0d522000a1f970a_5.jpg","width":150,"height":150},"standard_resolution":{"url":"http:\/\/distilleryimage5.s3.amazonaws.com\/8077de707d0c11e2a0d522000a1f970a_7.jpg","width":612,"height":612}},"caption":null,"user_has_liked":false,"id":"397035505961591789_203110951","user":{"username":"pelletized","website":"","profile_picture":"http:\/\/images.instagram.com\/profiles\/profile_203110951_75sq_1361336165.jpg","full_name":"ed w","bio":"","id":"203110951"}},{"attribution":null,"tags":["instago","river","clouds","love","cool","instabest","sky","all_shots","instagood","snapseed","bestoftheday","daily","jj","statigram","art","instadaily","webstagram","picoftheday","best","photooftheday"],"type":"image","location":null,"comments":{"count":2,"data":[{"created_time":"1361414706","text":"#cool #love #bestoftheday #picoftheday #photooftheday #all_shots #art","from":{"username":"pelletized","profile_picture":"http:\/\/images.instagram.com\/profiles\/profile_203110951_75sq_1361336165.jpg","id":"203110951","full_name":"ed w"},"id":"395897709658038401"},{"created_time":"1361414931","text":"#daily #instadaily #instago #instagood #instabest #best","from":{"username":"pelletized","profile_picture":"http:\/\/images.instagram.com\/profiles\/profile_203110951_75sq_1361336165.jpg","id":"203110951","full_name":"ed w"},"id":"395899600039239909"}]},"filter":"Normal","created_time":"1361414468","link":"http:\/\/instagr.am\/p\/V-gQ3ojuIT\/","likes":{"count":55,"data":[{"username":"suzbee_boston","profile_picture":"http:\/\/images.instagram.com\/profiles\/profile_226116_75sq_1337914634.jpg","id":"226116","full_name":"Suzanne Brendle"},{"username":"sarahbordeau","profile_picture":"http:\/\/images.instagram.com\/profiles\/profile_180704647_75sq_1361129871.jpg","id":"180704647","full_name":"Sarah Bordeau"},{"username":"vincenzd","profile_picture":"http:\/\/images.instagram.com\/profiles\/profile_200282792_75sq_1343512064.jpg","id":"200282792","full_name":"vincenzd"},{"username":"blondie81905","profile_picture":"http:\/\/images.instagram.com\/profiles\/profile_254788843_75sq_1353200412.jpg","id":"254788843","full_name":"Erika Toner"},{"username":"kaymac09","profile_picture":"http:\/\/images.instagram.com\/profiles\/profile_31071213_75sq_1355532220.jpg","id":"31071213","full_name":"kaymac09"},{"username":"mootskie","profile_picture":"http:\/\/images.instagram.com\/profiles\/profile_22931278_75sq_1361455324.jpg","id":"22931278","full_name":"Jonathan"},{"username":"yukinyc","profile_picture":"http:\/\/images.instagram.com\/profiles\/profile_204584848_75sq_1358214638.jpg","id":"204584848","full_name":"yuki"},{"username":"deborahrin","profile_picture":"http:\/\/images.instagram.com\/profiles\/profile_55567175_75sq_1359991414.jpg","id":"55567175","full_name":"Deborah Rinaldo"},{"username":"featherhb711","profile_picture":"http:\/\/images.instagram.com\/profiles\/profile_49996890_75sq_1360198784.jpg","id":"49996890","full_name":"Heather Booth"},{"username":"beautifull_world13","profile_picture":"http:\/\/images.instagram.com\/profiles\/profile_294408314_75sq_1361547273.jpg","id":"294408314","full_name":"\ud83d\udc93\ud83d\udc9eBeautiful World\ud83d\udc9e\ud83d\udc93"}]},"images":{"low_resolution":{"url":"http:\/\/distilleryimage7.s3.amazonaws.com\/25611b927bd011e299af22000a9e29bc_6.jpg","width":306,"height":306},"thumbnail":{"url":"http:\/\/distilleryimage7.s3.amazonaws.com\/25611b927bd011e299af22000a9e29bc_5.jpg","width":150,"height":150},"standard_resolution":{"url":"http:\/\/distilleryimage7.s3.amazonaws.com\/25611b927bd011e299af22000a9e29bc_7.jpg","width":612,"height":612}},"caption":{"created_time":"1361414527","text":"#river #sky #clouds #jj #webstagram #statigram  #Snapseed","from":{"username":"pelletized","profile_picture":"http:\/\/images.instagram.com\/profiles\/profile_203110951_75sq_1361336165.jpg","id":"203110951","full_name":"ed w"},"id":"395896210899001415"},"user_has_liked":false,"id":"395895713991418387_203110951","user":{"username":"pelletized","website":"","profile_picture":"http:\/\/images.instagram.com\/profiles\/profile_203110951_75sq_1361336165.jpg","full_name":"ed w","bio":"","id":"203110951"}},{"attribution":null,"tags":["newyorkcity","newyork","teg","wtc","texture","jj","bestofnewyork","jj_forum","streetphotography","clouds","scenic","sky","all_shots","manhattan","skyline","snapseed","bestoftheday","statigram","nyc","webstagram","picoftheday","photooftheday"],"type":"image","location":{"latitude":40.7292229,"longitude":-73.9956123},"comments":{"count":8,"data":[{"created_time":"1361379782","text":"#clouds #sky #scenic #all_shots #bestoftheday #picoftheday #photooftheday","from":{"username":"pelletized","profile_picture":"http:\/\/images.instagram.com\/profiles\/profile_203110951_75sq_1361336165.jpg","id":"203110951","full_name":"ed w"},"id":"395604746667221017"},{"created_time":"1361388175","text":"Cool shot!! \ud83d\udc4d\ud83d\udc4d","from":{"username":"mootskie","profile_picture":"http:\/\/images.instagram.com\/profiles\/profile_22931278_75sq_1361455324.jpg","id":"22931278","full_name":"Jonathan"},"id":"395675154493923481"},{"created_time":"1361390728","text":"@mootskie thanks!","from":{"username":"pelletized","profile_picture":"http:\/\/images.instagram.com\/profiles\/profile_203110951_75sq_1361336165.jpg","id":"203110951","full_name":"ed w"},"id":"395696572237538104"},{"created_time":"1361390762","text":"#texture #teg","from":{"username":"pelletized","profile_picture":"http:\/\/images.instagram.com\/profiles\/profile_203110951_75sq_1361336165.jpg","id":"203110951","full_name":"ed w"},"id":"395696853926994766"},{"created_time":"1361395012","text":"#wtc #skyline","from":{"username":"pelletized","profile_picture":"http:\/\/images.instagram.com\/profiles\/profile_203110951_75sq_1361336165.jpg","id":"203110951","full_name":"ed w"},"id":"395732507759140901"},{"created_time":"1361396748","text":"#bestofnewyork","from":{"username":"pelletized","profile_picture":"http:\/\/images.instagram.com\/profiles\/profile_203110951_75sq_1361336165.jpg","id":"203110951","full_name":"ed w"},"id":"395747065508848199"},{"created_time":"1361406260","text":"Like that texture.","from":{"username":"vkconk","profile_picture":"http:\/\/images.instagram.com\/profiles\/profile_104802054_75sq_1337142042.jpg","id":"104802054","full_name":"Vicki"},"id":"395826861353919393"},{"created_time":"1361554745","text":"@vkconk thanks!","from":{"username":"pelletized","profile_picture":"http:\/\/images.instagram.com\/profiles\/profile_203110951_75sq_1361336165.jpg","id":"203110951","full_name":"ed w"},"id":"397072441002615349"}]},"filter":"Normal","created_time":"1361379611","link":"http:\/\/instagr.am\/p\/V9dx3MDuJb\/","likes":{"count":50,"data":[{"username":"jwheels45","profile_picture":"http:\/\/images.instagram.com\/profiles\/profile_205606283_75sq_1346468328.jpg","id":"205606283","full_name":"jwheels45"},{"username":"ticoaa","profile_picture":"http:\/\/images.instagram.com\/profiles\/profile_1081445_75sq_1358741933.jpg","id":"1081445","full_name":"\u24b6\u24c1\u24b7\u24ba\u24c7\u24c9"},{"username":"vkconk","profile_picture":"http:\/\/images.instagram.com\/profiles\/profile_104802054_75sq_1337142042.jpg","id":"104802054","full_name":"Vicki"},{"username":"deborahrin","profile_picture":"http:\/\/images.instagram.com\/profiles\/profile_55567175_75sq_1359991414.jpg","id":"55567175","full_name":"Deborah Rinaldo"},{"username":"blondie81905","profile_picture":"http:\/\/images.instagram.com\/profiles\/profile_254788843_75sq_1353200412.jpg","id":"254788843","full_name":"Erika Toner"},{"username":"mkeahey","profile_picture":"http:\/\/images.instagram.com\/profiles\/profile_246956109_75sq_1353105806.jpg","id":"246956109","full_name":"Mark Keahey"},{"username":"carlagirlnj","profile_picture":"http:\/\/images.instagram.com\/profiles\/profile_202038544_75sq_1343852223.jpg","id":"202038544","full_name":"Carla Jeffrey"},{"username":"alyssas90","profile_picture":"http:\/\/images.instagram.com\/profiles\/profile_185851610_75sq_1340506677.jpg","id":"185851610","full_name":"alyssas90"},{"username":"jennibug44","profile_picture":"http:\/\/images.instagram.com\/profiles\/profile_211903195_75sq_1358994813.jpg","id":"211903195","full_name":"jennibug44"},{"username":"leighb1987","profile_picture":"http:\/\/images.instagram.com\/profiles\/profile_182523482_75sq_1350610287.jpg","id":"182523482","full_name":"\ud83c\udf34\u2600\ud83c\udf37"}]},"images":{"low_resolution":{"url":"http:\/\/distilleryimage3.s3.amazonaws.com\/fcf934427b7e11e28fba22000a1fb1a7_6.jpg","width":306,"height":306},"thumbnail":{"url":"http:\/\/distilleryimage3.s3.amazonaws.com\/fcf934427b7e11e28fba22000a1fb1a7_5.jpg","width":150,"height":150},"standard_resolution":{"url":"http:\/\/distilleryimage3.s3.amazonaws.com\/fcf934427b7e11e28fba22000a1fb1a7_7.jpg","width":612,"height":612}},"caption":{"created_time":"1361379699","text":"#statigram #snapseed #webstagram #jj #jj_forum #newyorkcity #newyork #nyc #streetphotography #manhattan","from":{"username":"pelletized","profile_picture":"http:\/\/images.instagram.com\/profiles\/profile_203110951_75sq_1361336165.jpg","id":"203110951","full_name":"ed w"},"id":"395604054154077173"},"user_has_liked":false,"id":"395603312139756123_203110951","user":{"username":"pelletized","website":"","profile_picture":"http:\/\/images.instagram.com\/profiles\/profile_203110951_75sq_1361336165.jpg","full_name":"ed w","bio":"","id":"203110951"}},{"attribution":null,"tags":["igersnyc","art","newyorkcity","newyork","instalike","instalove","brooklyn","graffiti","instabest","jj","love","streetart","instago","igersofnyc","urbanart","clouds","longexposure","sky","all_shots","instagood","lights","snapseed","bestoftheday","2013","statigram","nyc","webstagram","picoftheday","red","photooftheday"],"type":"image","location":null,"comments":{"count":5,"data":[{"created_time":"1361334055","text":"#picoftheday #photooftheday #all_shots #bestoftheday #love","from":{"username":"pelletized","profile_picture":"http:\/\/images.instagram.com\/profiles\/profile_203110951_75sq_1361336165.jpg","id":"203110951","full_name":"ed w"},"id":"395221161418351473"},{"created_time":"1361334317","text":"#art #streetart #graffiti #urbanart","from":{"username":"pelletized","profile_picture":"http:\/\/images.instagram.com\/profiles\/profile_203110951_75sq_1361336165.jpg","id":"203110951","full_name":"ed w"},"id":"395223359913124800"},{"created_time":"1361334755","text":"#clouds #sky #red","from":{"username":"pelletized","profile_picture":"http:\/\/images.instagram.com\/profiles\/profile_203110951_75sq_1361336165.jpg","id":"203110951","full_name":"ed w"},"id":"395227036799393844"},{"created_time":"1361334965","text":"#instago #igersnyc #igersofnyc #instagood","from":{"username":"pelletized","profile_picture":"http:\/\/images.instagram.com\/profiles\/profile_203110951_75sq_1361336165.jpg","id":"203110951","full_name":"ed w"},"id":"395228795311677549"},{"created_time":"1361362092","text":"#2013 #instabest #instalike #instalove #longexposure","from":{"username":"pelletized","profile_picture":"http:\/\/images.instagram.com\/profiles\/profile_203110951_75sq_1361336165.jpg","id":"203110951","full_name":"ed w"},"id":"395456356125958544"}]},"filter":"Normal","created_time":"1361333865","link":"http:\/\/instagr.am\/p\/V8GhrNjuLe\/","likes":{"count":67,"data":[{"username":"ceos_downbeat","profile_picture":"http:\/\/images.instagram.com\/profiles\/profile_28051264_75sq_1359581957.jpg","id":"28051264","full_name":"ceos_downbeat"},{"username":"coloresdelavida","profile_picture":"http:\/\/images.instagram.com\/profiles\/profile_30625922_75sq_1361539942.jpg","id":"30625922","full_name":"Sirio Rosario Camacho"},{"username":"deborahrin","profile_picture":"http:\/\/images.instagram.com\/profiles\/profile_55567175_75sq_1359991414.jpg","id":"55567175","full_name":"Deborah Rinaldo"},{"username":"pao0oliita","profile_picture":"http:\/\/images.instagram.com\/profiles\/profile_257734664_75sq_1355231407.jpg","id":"257734664","full_name":"P@0la"},{"username":"blondie81905","profile_picture":"http:\/\/images.instagram.com\/profiles\/profile_254788843_75sq_1353200412.jpg","id":"254788843","full_name":"Erika Toner"},{"username":"chphotography_","profile_picture":"http:\/\/images.instagram.com\/profiles\/profile_7931362_75sq_1361462851.jpg","id":"7931362","full_name":"Christian"},{"username":"yukinyc","profile_picture":"http:\/\/images.instagram.com\/profiles\/profile_204584848_75sq_1358214638.jpg","id":"204584848","full_name":"yuki"},{"username":"memegramer","profile_picture":"http:\/\/images.instagram.com\/profiles\/profile_260500536_75sq_1354131621.jpg","id":"260500536","full_name":"funny smith"},{"username":"leighb1987","profile_picture":"http:\/\/images.instagram.com\/profiles\/profile_182523482_75sq_1350610287.jpg","id":"182523482","full_name":"\ud83c\udf34\u2600\ud83c\udf37"},{"username":"alyssas90","profile_picture":"http:\/\/images.instagram.com\/profiles\/profile_185851610_75sq_1340506677.jpg","id":"185851610","full_name":"alyssas90"}]},"images":{"low_resolution":{"url":"http:\/\/distilleryimage10.s3.amazonaws.com\/7a71e54c7b1411e28d0622000a9e13b7_6.jpg","width":306,"height":306},"thumbnail":{"url":"http:\/\/distilleryimage10.s3.amazonaws.com\/7a71e54c7b1411e28d0622000a9e13b7_5.jpg","width":150,"height":150},"standard_resolution":{"url":"http:\/\/distilleryimage10.s3.amazonaws.com\/7a71e54c7b1411e28d0622000a9e13b7_7.jpg","width":612,"height":612}},"caption":{"created_time":"1361333946","text":"#Snapseed #webstagram #statigram #jj #lights #brooklyn #nyc #newyorkcity #newyork","from":{"username":"pelletized","profile_picture":"http:\/\/images.instagram.com\/profiles\/profile_203110951_75sq_1361336165.jpg","id":"203110951","full_name":"ed w"},"id":"395220248326759245"},"user_has_liked":false,"id":"395219569721926366_203110951","user":{"username":"pelletized","website":"","profile_picture":"http:\/\/images.instagram.com\/profiles\/profile_203110951_75sq_1361336165.jpg","full_name":"ed w","bio":"","id":"203110951"}},{"attribution":null,"tags":["funny","urbanart","love","streetart","awesome","doylestown","snapseed","graffiti","all_shots","jj","statigram","webstagram","lol"],"type":"image","location":{"latitude":40.308036804,"longitude":-75.129371643},"comments":{"count":1,"data":[{"created_time":"1361208764","text":"#graffiti #jj #all_shots #awesome #funny #lol #love","from":{"username":"pelletized","profile_picture":"http:\/\/images.instagram.com\/profiles\/profile_203110951_75sq_1361336165.jpg","id":"203110951","full_name":"ed w"},"id":"394170144148873540"}]},"filter":"Normal","created_time":"1361142132","link":"http:\/\/instagr.am\/p\/V2Y0xEDuAN\/","likes":{"count":41,"data":[{"username":"aabadee13","profile_picture":"http:\/\/images.instagram.com\/profiles\/profile_22877217_75sq_1359788023.jpg","id":"22877217","full_name":"Alexa Nicole Abadee"},{"username":"coloresdelavida","profile_picture":"http:\/\/images.instagram.com\/profiles\/profile_30625922_75sq_1361539942.jpg","id":"30625922","full_name":"Sirio Rosario Camacho"},{"username":"theunicow","profile_picture":"http:\/\/images.instagram.com\/profiles\/profile_211028677_75sq_1345513990.jpg","id":"211028677","full_name":"theunicow"},{"username":"ryman03","profile_picture":"http:\/\/images.instagram.com\/profiles\/profile_55264424_75sq_1336927623.jpg","id":"55264424","full_name":"Ryan Byrd"},{"username":"tstav","profile_picture":"http:\/\/images.instagram.com\/profiles\/profile_214026857_75sq_1361172086.jpg","id":"214026857","full_name":"Thanasi Stav"},{"username":"blondie81905","profile_picture":"http:\/\/images.instagram.com\/profiles\/profile_254788843_75sq_1353200412.jpg","id":"254788843","full_name":"Erika Toner"},{"username":"pao0oliita","profile_picture":"http:\/\/images.instagram.com\/profiles\/profile_257734664_75sq_1355231407.jpg","id":"257734664","full_name":"P@0la"},{"username":"memegramer","profile_picture":"http:\/\/images.instagram.com\/profiles\/profile_260500536_75sq_1354131621.jpg","id":"260500536","full_name":"funny smith"},{"username":"its_andrean","profile_picture":"http:\/\/images.instagram.com\/profiles\/profile_271857247_75sq_1360506146.jpg","id":"271857247","full_name":"Andrea Newland"},{"username":"ticoaa","profile_picture":"http:\/\/images.instagram.com\/profiles\/profile_1081445_75sq_1358741933.jpg","id":"1081445","full_name":"\u24b6\u24c1\u24b7\u24ba\u24c7\u24c9"}]},"images":{"low_resolution":{"url":"http:\/\/distilleryimage5.s3.amazonaws.com\/10aaa1c2795611e2aadd22000a1fbd6a_6.jpg","width":306,"height":306},"thumbnail":{"url":"http:\/\/distilleryimage5.s3.amazonaws.com\/10aaa1c2795611e2aadd22000a1fbd6a_5.jpg","width":150,"height":150},"standard_resolution":{"url":"http:\/\/distilleryimage5.s3.amazonaws.com\/10aaa1c2795611e2aadd22000a1fbd6a_7.jpg","width":612,"height":612}},"caption":{"created_time":"1361142213","text":"#snapseed #streetart #statigram #webstagram #urbanart #doylestown","from":{"username":"pelletized","profile_picture":"http:\/\/images.instagram.com\/profiles\/profile_203110951_75sq_1361336165.jpg","id":"203110951","full_name":"ed w"},"id":"393611871322562841"},"user_has_liked":false,"id":"393611196651986957_203110951","user":{"username":"pelletized","website":"","profile_picture":"http:\/\/images.instagram.com\/profiles\/profile_203110951_75sq_1361336165.jpg","full_name":"ed w","bio":"","id":"203110951"}},{"attribution":null,"tags":["newyorkcity","newyork","picoftheday","snapseed","statigram","nyc","webstagram","manhattan","photooftheday"],"type":"image","location":{"latitude":40.7287029,"longitude":-73.999467},"comments":{"count":5,"data":[{"created_time":"1360971611","text":"We are gonna be at the met tomorrow ... U should meet us. @pelletized","from":{"username":"tonyajoanne","profile_picture":"http:\/\/images.instagram.com\/profiles\/profile_183679620_75sq_1360061713.jpg","id":"183679620","full_name":"tonyajoanne"},"id":"392180763179540896"},{"created_time":"1360973899","text":"@tonyajoanne wish I could but I'm at my parents this weekend! Have a great time!","from":{"username":"pelletized","profile_picture":"http:\/\/images.instagram.com\/profiles\/profile_203110951_75sq_1361336165.jpg","id":"203110951","full_name":"ed w"},"id":"392199949159161934"},{"created_time":"1360974328","text":"My fav people send my love and have fun! @pelletized","from":{"username":"tonyajoanne","profile_picture":"http:\/\/images.instagram.com\/profiles\/profile_183679620_75sq_1360061713.jpg","id":"183679620","full_name":"tonyajoanne"},"id":"392203552057909439"},{"created_time":"1361134429","text":"Lovely!!!","from":{"username":"carokaramel","profile_picture":"http:\/\/images.instagram.com\/profiles\/profile_8976862_75sq_1359170793.jpg","id":"8976862","full_name":"\u24d2\u24d0\u24e1\u24de\u24db\u24d8\u24dd\u24d0"},"id":"393546578902573725"},{"created_time":"1361139506","text":"@carokaramel thank you!","from":{"username":"pelletized","profile_picture":"http:\/\/images.instagram.com\/profiles\/profile_203110951_75sq_1361336165.jpg","id":"203110951","full_name":"ed w"},"id":"393589164233122209"}]},"filter":"Normal","created_time":"1360967630","link":"http:\/\/instagr.am\/p\/VxL_N9juLG\/","likes":{"count":47,"data":[{"username":"coloresdelavida","profile_picture":"http:\/\/images.instagram.com\/profiles\/profile_30625922_75sq_1361539942.jpg","id":"30625922","full_name":"Sirio Rosario Camacho"},{"username":"ticoaa","profile_picture":"http:\/\/images.instagram.com\/profiles\/profile_1081445_75sq_1358741933.jpg","id":"1081445","full_name":"\u24b6\u24c1\u24b7\u24ba\u24c7\u24c9"},{"username":"pao0oliita","profile_picture":"http:\/\/images.instagram.com\/profiles\/profile_257734664_75sq_1355231407.jpg","id":"257734664","full_name":"P@0la"},{"username":"tstav","profile_picture":"http:\/\/images.instagram.com\/profiles\/profile_214026857_75sq_1361172086.jpg","id":"214026857","full_name":"Thanasi Stav"},{"username":"blondie81905","profile_picture":"http:\/\/images.instagram.com\/profiles\/profile_254788843_75sq_1353200412.jpg","id":"254788843","full_name":"Erika Toner"},{"username":"mkeahey","profile_picture":"http:\/\/images.instagram.com\/profiles\/profile_246956109_75sq_1353105806.jpg","id":"246956109","full_name":"Mark Keahey"},{"username":"yukinyc","profile_picture":"http:\/\/images.instagram.com\/profiles\/profile_204584848_75sq_1358214638.jpg","id":"204584848","full_name":"yuki"},{"username":"fernandinhacruz","profile_picture":"http:\/\/images.instagram.com\/profiles\/profile_178345298_75sq_1347308288.jpg","id":"178345298","full_name":"fernandinhacruz"},{"username":"memegramer","profile_picture":"http:\/\/images.instagram.com\/profiles\/profile_260500536_75sq_1354131621.jpg","id":"260500536","full_name":"funny smith"},{"username":"carokaramel","profile_picture":"http:\/\/images.instagram.com\/profiles\/profile_8976862_75sq_1359170793.jpg","id":"8976862","full_name":"\u24d2\u24d0\u24e1\u24de\u24db\u24d8\u24dd\u24d0"}]},"images":{"low_resolution":{"url":"http:\/\/distilleryimage10.s3.amazonaws.com\/c533604077bf11e2a7ab22000a1f97eb_6.jpg","width":306,"height":306},"thumbnail":{"url":"http:\/\/distilleryimage10.s3.amazonaws.com\/c533604077bf11e2a7ab22000a1f97eb_5.jpg","width":150,"height":150},"standard_resolution":{"url":"http:\/\/distilleryimage10.s3.amazonaws.com\/c533604077bf11e2a7ab22000a1f97eb_7.jpg","width":612,"height":612}},"caption":{"created_time":"1360967699","text":"#nyc #newyorkcity #newyork #manhattan #snapseed #webstagram #statigram #picoftheday #photooftheday","from":{"username":"pelletized","profile_picture":"http:\/\/images.instagram.com\/profiles\/profile_203110951_75sq_1361336165.jpg","id":"203110951","full_name":"ed w"},"id":"392147944982110500"},"user_has_liked":false,"id":"392147365388018374_203110951","user":{"username":"pelletized","website":"","profile_picture":"http:\/\/images.instagram.com\/profiles\/profile_203110951_75sq_1361336165.jpg","full_name":"ed w","bio":"","id":"203110951"}},{"attribution":null,"tags":["funny","webstagram","snapseed","lol","statigram"],"type":"image","location":{"latitude":40.728710175,"longitude":-73.995620728},"comments":{"count":10,"data":[{"created_time":"1360962114","text":"Perfect for the day after, especially if you've forgotten THE day. :(","from":{"username":"emaeburn","profile_picture":"http:\/\/images.instagram.com\/profiles\/profile_205043569_75sq_1361762733.jpg","id":"205043569","full_name":"Elaine Godburn"},"id":"392101092031128123"},{"created_time":"1360962992","text":"@jer1978 @jmjudson @emaeburn some folks from comedy central were passing those out in front of the subway last night. they were good! and yes, i took candy from strangers ;p","from":{"username":"pelletized","profile_picture":"http:\/\/images.instagram.com\/profiles\/profile_203110951_75sq_1361336165.jpg","id":"203110951","full_name":"ed w"},"id":"392108457371558754"},{"created_time":"1360963671","text":"I'm gonna tell ur momma!!","from":{"username":"vkconk","profile_picture":"http:\/\/images.instagram.com\/profiles\/profile_104802054_75sq_1337142042.jpg","id":"104802054","full_name":"Vicki"},"id":"392114156155625527"},{"created_time":"1360963788","text":"That's awsum!!!!","from":{"username":"jmjudson","profile_picture":"http:\/\/images.instagram.com\/profiles\/profile_51754719_75sq_1361554309.jpg","id":"51754719","full_name":"jmjudson"},"id":"392115139703136348"},{"created_time":"1360964918","text":"You did what \ud83d\ude31","from":{"username":"jwheels45","profile_picture":"http:\/\/images.instagram.com\/profiles\/profile_205606283_75sq_1346468328.jpg","id":"205606283","full_name":"jwheels45"},"id":"392124615994827178"},{"created_time":"1360966005","text":"Lol!","from":{"username":"jennyr0508","profile_picture":"http:\/\/images.instagram.com\/profiles\/profile_295870840_75sq_1359642695.jpg","id":"295870840","full_name":"Jen Rubino"},"id":"392133737507119885"},{"created_time":"1360966088","text":"\ud83d\ude33","from":{"username":"leighb1987","profile_picture":"http:\/\/images.instagram.com\/profiles\/profile_182523482_75sq_1350610287.jpg","id":"182523482","full_name":"\ud83c\udf34\u2600\ud83c\udf37"},"id":"392134426270556966"},{"created_time":"1360967172","text":"@vkconk uh oh, @jwheels45 saw it","from":{"username":"pelletized","profile_picture":"http:\/\/images.instagram.com\/profiles\/profile_203110951_75sq_1361336165.jpg","id":"203110951","full_name":"ed w"},"id":"392143525234270323"}]},"filter":"Normal","created_time":"1360956748","link":"http:\/\/instagr.am\/p\/Vw3O1nDuCr\/","likes":{"count":33,"data":[{"username":"suzbee_boston","profile_picture":"http:\/\/images.instagram.com\/profiles\/profile_226116_75sq_1337914634.jpg","id":"226116","full_name":"Suzanne Brendle"},{"username":"ryman03","profile_picture":"http:\/\/images.instagram.com\/profiles\/profile_55264424_75sq_1336927623.jpg","id":"55264424","full_name":"Ryan Byrd"},{"username":"tstav","profile_picture":"http:\/\/images.instagram.com\/profiles\/profile_214026857_75sq_1361172086.jpg","id":"214026857","full_name":"Thanasi Stav"},{"username":"vincenzd","profile_picture":"http:\/\/images.instagram.com\/profiles\/profile_200282792_75sq_1343512064.jpg","id":"200282792","full_name":"vincenzd"},{"username":"carlagirlnj","profile_picture":"http:\/\/images.instagram.com\/profiles\/profile_202038544_75sq_1343852223.jpg","id":"202038544","full_name":"Carla Jeffrey"},{"username":"jesski4","profile_picture":"http:\/\/images.instagram.com\/profiles\/profile_226514865_75sq_1357414146.jpg","id":"226514865","full_name":"Jessica Krotowski"},{"username":"jennibug44","profile_picture":"http:\/\/images.instagram.com\/profiles\/profile_211903195_75sq_1358994813.jpg","id":"211903195","full_name":"jennibug44"},{"username":"shannanigan_93","profile_picture":"http:\/\/images.instagram.com\/profiles\/profile_193559292_75sq_1360984277.jpg","id":"193559292","full_name":"Shannon Keahey"},{"username":"dparke3","profile_picture":"http:\/\/images.instagram.com\/profiles\/profile_19320349_75sq_1358399824.jpg","id":"19320349","full_name":"Dave Parke III"},{"username":"its_andrean","profile_picture":"http:\/\/images.instagram.com\/profiles\/profile_271857247_75sq_1360506146.jpg","id":"271857247","full_name":"Andrea"}]},"images":{"low_resolution":{"url":"http:\/\/distilleryimage3.s3.amazonaws.com\/6ef79f6677a611e2843f22000a9e0722_6.jpg","width":306,"height":306},"thumbnail":{"url":"http:\/\/distilleryimage3.s3.amazonaws.com\/6ef79f6677a611e2843f22000a9e0722_5.jpg","width":150,"height":150},"standard_resolution":{"url":"http:\/\/distilleryimage3.s3.amazonaws.com\/6ef79f6677a611e2843f22000a9e0722_7.jpg","width":612,"height":612}},"caption":{"created_time":"1360956790","text":"#snapseed #webstagram #statigram #lol#funny","from":{"username":"pelletized","profile_picture":"http:\/\/images.instagram.com\/profiles\/profile_203110951_75sq_1361336165.jpg","id":"203110951","full_name":"ed w"},"id":"392056431459623049"},"user_has_liked":false,"id":"392056079775621291_203110951","user":{"username":"pelletized","website":"","profile_picture":"http:\/\/images.instagram.com\/profiles\/profile_203110951_75sq_1361336165.jpg","full_name":"ed w","bio":"","id":"203110951"}},{"attribution":null,"tags":["funny","urbanart","art","lol","lights","mirror","picoftheday","photooftheday"],"type":"image","location":{"latitude":40.7318706,"longitude":-73.9837483},"comments":{"count":3,"data":[{"created_time":"1360872198","text":"Look like Eddy Murphy.","from":{"username":"vkconk","profile_picture":"http:\/\/images.instagram.com\/profiles\/profile_104802054_75sq_1337142042.jpg","id":"104802054","full_name":"Vicki"},"id":"391346821358608766"},{"created_time":"1360897005","text":"@vkconk you got it!","from":{"username":"pelletized","profile_picture":"http:\/\/images.instagram.com\/profiles\/profile_203110951_75sq_1361336165.jpg","id":"203110951","full_name":"ed w"},"id":"391554917045559806"},{"created_time":"1360897065","text":"#funny #lol #art #urbanart #mirror #lights #picoftheday #photooftheday","from":{"username":"pelletized","profile_picture":"http:\/\/images.instagram.com\/profiles\/profile_203110951_75sq_1361336165.jpg","id":"203110951","full_name":"ed w"},"id":"391555419841946142"}]},"filter":"Sierra","created_time":"1360869484","link":"http:\/\/instagr.am\/p\/VuQyiPjuOh\/","likes":{"count":24,"data":[{"username":"joetoro","profile_picture":"http:\/\/images.instagram.com\/profiles\/profile_35193189_75sq_1361669205.jpg","id":"35193189","full_name":"Joe Toro"},{"username":"vkconk","profile_picture":"http:\/\/images.instagram.com\/profiles\/profile_104802054_75sq_1337142042.jpg","id":"104802054","full_name":"Vicki"},{"username":"vincenzd","profile_picture":"http:\/\/images.instagram.com\/profiles\/profile_200282792_75sq_1343512064.jpg","id":"200282792","full_name":"vincenzd"},{"username":"tstav","profile_picture":"http:\/\/images.instagram.com\/profiles\/profile_214026857_75sq_1361172086.jpg","id":"214026857","full_name":"Thanasi Stav"},{"username":"blondie81905","profile_picture":"http:\/\/images.instagram.com\/profiles\/profile_254788843_75sq_1353200412.jpg","id":"254788843","full_name":"Erika Toner"},{"username":"nephewcc","profile_picture":"http:\/\/images.instagram.com\/profiles\/profile_182921232_75sq_1358707681.jpg","id":"182921232","full_name":"Nephew Clothing Co."},{"username":"dipdyed_mustache","profile_picture":"http:\/\/images.instagram.com\/profiles\/profile_17930292_75sq_1361070831.jpg","id":"17930292","full_name":"! IM AWKWARD"},{"username":"kimmyks","profile_picture":"http:\/\/images.instagram.com\/profiles\/profile_5650458_75sq_1352598183.jpg","id":"5650458","full_name":"kimmyks"},{"username":"featherhb711","profile_picture":"http:\/\/images.instagram.com\/profiles\/profile_49996890_75sq_1360198784.jpg","id":"49996890","full_name":"Heather Booth"},{"username":"rocco_nyc","profile_picture":"http:\/\/images.instagram.com\/profiles\/profile_22996382_75sq_1361341006.jpg","id":"22996382","full_name":"- Rocco Gardner"}]},"images":{"low_resolution":{"url":"http:\/\/distilleryimage1.s3.amazonaws.com\/41c32c1676db11e2a07422000a1fab83_6.jpg","width":306,"height":306},"thumbnail":{"url":"http:\/\/distilleryimage1.s3.amazonaws.com\/41c32c1676db11e2a07422000a1fab83_5.jpg","width":150,"height":150},"standard_resolution":{"url":"http:\/\/distilleryimage1.s3.amazonaws.com\/41c32c1676db11e2a07422000a1fab83_7.jpg","width":612,"height":612}},"caption":null,"user_has_liked":false,"id":"391324059114070945_203110951","user":{"username":"pelletized","website":"","profile_picture":"http:\/\/images.instagram.com\/profiles\/profile_203110951_75sq_1361336165.jpg","full_name":"ed w","bio":"","id":"203110951"}},{"attribution":null,"tags":["urbanart","art","streetart","instafamous","awesome","teg","all_shots","instagood","snapseed","pretty","jj","statigram","love","webstagram","picoftheday","photooftheday"],"type":"image","location":{"latitude":40.738853455,"longitude":-74.005683899},"comments":{"count":1,"data":[{"created_time":"1360672394","text":"#instafamous #instagood #teg #pretty","from":{"username":"pelletized","profile_picture":"http:\/\/images.instagram.com\/profiles\/profile_203110951_75sq_1361336165.jpg","id":"203110951","full_name":"ed w"},"id":"389670745578332513"}]},"filter":null,"created_time":"1360618994","link":"http:\/\/instagr.am\/p\/VmzBJZDuMD\/","likes":{"count":34,"data":[{"username":"mason_krystopher","profile_picture":"http:\/\/images.instagram.com\/profiles\/profile_285668386_75sq_1361422285.jpg","id":"285668386","full_name":"\u261e3k KRYSTONYTES!\u261c"},{"username":"vkconk","profile_picture":"http:\/\/images.instagram.com\/profiles\/profile_104802054_75sq_1337142042.jpg","id":"104802054","full_name":"Vicki"},{"username":"ryman03","profile_picture":"http:\/\/images.instagram.com\/profiles\/profile_55264424_75sq_1336927623.jpg","id":"55264424","full_name":"Ryan Byrd"},{"username":"bethalane69","profile_picture":"http:\/\/images.instagram.com\/profiles\/profile_211826780_75sq_1360697361.jpg","id":"211826780","full_name":"Betha Lane"},{"username":"jwheels45","profile_picture":"http:\/\/images.instagram.com\/profiles\/profile_205606283_75sq_1346468328.jpg","id":"205606283","full_name":"jwheels45"},{"username":"danielnapolitano","profile_picture":"http:\/\/images.instagram.com\/profiles\/profile_22326703_75sq_1360723302.jpg","id":"22326703","full_name":"Daniel Napolitano \"DNap\""},{"username":"vincenzd","profile_picture":"http:\/\/images.instagram.com\/profiles\/profile_200282792_75sq_1343512064.jpg","id":"200282792","full_name":"vincenzd"},{"username":"kimmyks","profile_picture":"http:\/\/images.instagram.com\/profiles\/profile_5650458_75sq_1352598183.jpg","id":"5650458","full_name":"kimmyks"},{"username":"shannabelle93","profile_picture":"http:\/\/images.instagram.com\/profiles\/profile_193559292_75sq_1361472646.jpg","id":"193559292","full_name":"Shannon Keahey"},{"username":"herestoyoujulirobinson","profile_picture":"http:\/\/images.instagram.com\/profiles\/profile_269545694_75sq_1361120724.jpg","id":"269545694","full_name":"juli hans"}]},"images":{"low_resolution":{"url":"http:\/\/distilleryimage11.s3.amazonaws.com\/0a1b3068749411e28a2e22000a1fbc67_6.jpg","width":306,"height":306},"thumbnail":{"url":"http:\/\/distilleryimage11.s3.amazonaws.com\/0a1b3068749411e28a2e22000a1fbc67_5.jpg","width":150,"height":150},"standard_resolution":{"url":"http:\/\/distilleryimage11.s3.amazonaws.com\/0a1b3068749411e28a2e22000a1fbc67_7.jpg","width":612,"height":612}},"caption":{"created_time":"1360619088","text":"#statigram #snapseed #webstagram #streetart #urbanart #art #all_shots #jj #awesome #love #picoftheday #photooftheday","from":{"username":"pelletized","profile_picture":"http:\/\/images.instagram.com\/profiles\/profile_203110951_75sq_1361336165.jpg","id":"203110951","full_name":"ed w"},"id":"389223586340987330"},"user_has_liked":false,"id":"389222796989752067_203110951","user":{"username":"pelletized","website":"","profile_picture":"http:\/\/images.instagram.com\/profiles\/profile_203110951_75sq_1361336165.jpg","full_name":"ed w","bio":"","id":"203110951"}},{"attribution":null,"tags":["love","newyork","iconic","teg","tag","jj","best","instasky","urbanart","clouds","like","bestagram","sky","all_shots","picoftheday","woolworthbuilding","snapseed","bestoftheday","architecture","statigram","nyc","webstagram","manhattan","photooftheday"],"type":"image","location":null,"comments":{"count":6,"data":[{"created_time":"1360557023","text":"#clouds #sky #nyc #newyork #manhattan #woolworthbuilding","from":{"username":"pelletized","profile_picture":"http:\/\/images.instagram.com\/profiles\/profile_203110951_75sq_1361336165.jpg","id":"203110951","full_name":"ed w"},"id":"388702942528463512"},{"created_time":"1360557146","text":"#architecture #iconic #urbanart","from":{"username":"pelletized","profile_picture":"http:\/\/images.instagram.com\/profiles\/profile_203110951_75sq_1361336165.jpg","id":"203110951","full_name":"ed w"},"id":"388703975711367869"},{"created_time":"1360558834","text":"#teg #tag #love #like #instasky","from":{"username":"pelletized","profile_picture":"http:\/\/images.instagram.com\/profiles\/profile_203110951_75sq_1361336165.jpg","id":"203110951","full_name":"ed w"},"id":"388718132569497741"},{"created_time":"1360561929","text":"#all_shots","from":{"username":"pelletized","profile_picture":"http:\/\/images.instagram.com\/profiles\/profile_203110951_75sq_1361336165.jpg","id":"203110951","full_name":"ed w"},"id":"388744099287458688"},{"created_time":"1361372290","text":"Nice picture!","from":{"username":"marina_june","profile_picture":"http:\/\/images.instagram.com\/profiles\/profile_33300180_75sq_1359651454.jpg","id":"33300180","full_name":"Marina June"},"id":"395541896229740845"},{"created_time":"1361374143","text":"@marina_june thank you!","from":{"username":"pelletized","profile_picture":"http:\/\/images.instagram.com\/profiles\/profile_203110951_75sq_1361336165.jpg","id":"203110951","full_name":"ed w"},"id":"395557440286810776"}]},"filter":"Normal","created_time":"1360556904","link":"http:\/\/instagr.am\/p\/Vk8ltZjuMD\/","likes":{"count":64,"data":[{"username":"_kj_kramer","profile_picture":"http:\/\/images.instagram.com\/profiles\/profile_207912064_75sq_1359332446.jpg","id":"207912064","full_name":"KJ Kramer"},{"username":"vkconk","profile_picture":"http:\/\/images.instagram.com\/profiles\/profile_104802054_75sq_1337142042.jpg","id":"104802054","full_name":"Vicki"},{"username":"deborahrin","profile_picture":"http:\/\/images.instagram.com\/profiles\/profile_55567175_75sq_1359991414.jpg","id":"55567175","full_name":"Deborah Rinaldo"},{"username":"ryman03","profile_picture":"http:\/\/images.instagram.com\/profiles\/profile_55264424_75sq_1336927623.jpg","id":"55264424","full_name":"Ryan Byrd"},{"username":"paulanthonyjohns_nyc","profile_picture":"http:\/\/images.instagram.com\/profiles\/profile_16137392_75sq_1360286054.jpg","id":"16137392","full_name":"Paul Johns"},{"username":"vincenzd","profile_picture":"http:\/\/images.instagram.com\/profiles\/profile_200282792_75sq_1343512064.jpg","id":"200282792","full_name":"vincenzd"},{"username":"fernandinhacruz","profile_picture":"http:\/\/images.instagram.com\/profiles\/profile_178345298_75sq_1347308288.jpg","id":"178345298","full_name":"fernandinhacruz"},{"username":"red1elm","profile_picture":"http:\/\/images.instagram.com\/profiles\/profile_254123284_75sq_1353811412.jpg","id":"254123284","full_name":"Red Elm"},{"username":"iviiv","profile_picture":"http:\/\/images.instagram.com\/profiles\/profile_9176341_75sq_1336160705.jpg","id":"9176341","full_name":"Magdalena N"},{"username":"marina_june","profile_picture":"http:\/\/images.instagram.com\/profiles\/profile_33300180_75sq_1359651454.jpg","id":"33300180","full_name":"Marina June"}]},"images":{"low_resolution":{"url":"http:\/\/distilleryimage11.s3.amazonaws.com\/7923f508740311e2aee522000a9f15b9_6.jpg","width":306,"height":306},"thumbnail":{"url":"http:\/\/distilleryimage11.s3.amazonaws.com\/7923f508740311e2aee522000a9f15b9_5.jpg","width":150,"height":150},"standard_resolution":{"url":"http:\/\/distilleryimage11.s3.amazonaws.com\/7923f508740311e2aee522000a9f15b9_7.jpg","width":612,"height":612}},"caption":{"created_time":"1360556952","text":"#Snapseed #webstagram #statigram #best #bestagram #bestoftheday #picoftheday #photooftheday  #jj","from":{"username":"pelletized","profile_picture":"http:\/\/images.instagram.com\/profiles\/profile_203110951_75sq_1361336165.jpg","id":"203110951","full_name":"ed w"},"id":"388702348690514561"},"user_has_liked":false,"id":"388701942019187459_203110951","user":{"username":"pelletized","website":"","profile_picture":"http:\/\/images.instagram.com\/profiles\/profile_203110951_75sq_1361336165.jpg","full_name":"ed w","bio":"","id":"203110951"}},{"attribution":null,"tags":["instaclouds","love","newyork","lookingup","awesome","instalike","bestoftheday","colors","lol","jj","instalove","lookup","best","instaart","clouds","like","bestagram","sky","watertower","winning","instasky","snapseed","sunset","statigram","fun","nyc","webstagram","soft","manhattan"],"type":"image","location":null,"comments":{"count":3,"data":[{"created_time":"1360538240","text":"#soft #colors #webstagram #winning #statigram #lookup #lookingup","from":{"username":"pelletized","profile_picture":"http:\/\/images.instagram.com\/profiles\/profile_203110951_75sq_1361336165.jpg","id":"203110951","full_name":"ed w"},"id":"388545379145016164"},{"created_time":"1360538381","text":"#instaclouds #instasky #instaart #like #love #fun #awesome #lol #instalike #instalove","from":{"username":"pelletized","profile_picture":"http:\/\/images.instagram.com\/profiles\/profile_203110951_75sq_1361336165.jpg","id":"203110951","full_name":"ed w"},"id":"388546565562622861"},{"created_time":"1360539008","text":"#best #bestagram #bestoftheday","from":{"username":"pelletized","profile_picture":"http:\/\/images.instagram.com\/profiles\/profile_203110951_75sq_1361336165.jpg","id":"203110951","full_name":"ed w"},"id":"388551819456864331"}]},"filter":"Normal","created_time":"1360538008","link":"http:\/\/instagr.am\/p\/VkYjHSjuL2\/","likes":{"count":49,"data":[{"username":"tonyajoanne","profile_picture":"http:\/\/images.instagram.com\/profiles\/profile_183679620_75sq_1360061713.jpg","id":"183679620","full_name":"tonyajoanne"},{"username":"vkconk","profile_picture":"http:\/\/images.instagram.com\/profiles\/profile_104802054_75sq_1337142042.jpg","id":"104802054","full_name":"Vicki"},{"username":"deborahrin","profile_picture":"http:\/\/images.instagram.com\/profiles\/profile_55567175_75sq_1359991414.jpg","id":"55567175","full_name":"Deborah Rinaldo"},{"username":"ryman03","profile_picture":"http:\/\/images.instagram.com\/profiles\/profile_55264424_75sq_1336927623.jpg","id":"55264424","full_name":"Ryan Byrd"},{"username":"mootskie","profile_picture":"http:\/\/images.instagram.com\/profiles\/profile_22931278_75sq_1361455324.jpg","id":"22931278","full_name":"Jonathan"},{"username":"reenie83","profile_picture":"http:\/\/images.instagram.com\/profiles\/profile_193758191_75sq_1345048879.jpg","id":"193758191","full_name":"reenie83"},{"username":"colorvu","profile_picture":"http:\/\/images.instagram.com\/profiles\/profile_2998382_75sq_1357688887.jpg","id":"2998382","full_name":"colorvu"},{"username":"leighb1987","profile_picture":"http:\/\/images.instagram.com\/profiles\/profile_182523482_75sq_1350610287.jpg","id":"182523482","full_name":"\ud83c\udf34\u2600\ud83c\udf37"},{"username":"asdfg_hi","profile_picture":"http:\/\/images.instagram.com\/profiles\/profile_279517583_75sq_1361251396.jpg","id":"279517583","full_name":"Sonny Lion"},{"username":"its_andrean","profile_picture":"http:\/\/images.instagram.com\/profiles\/profile_271857247_75sq_1360506146.jpg","id":"271857247","full_name":"Andrea"}]},"images":{"low_resolution":{"url":"http:\/\/distilleryimage2.s3.amazonaws.com\/7a76e43273d711e2ad1922000a1cbd31_6.jpg","width":306,"height":306},"thumbnail":{"url":"http:\/\/distilleryimage2.s3.amazonaws.com\/7a76e43273d711e2ad1922000a1cbd31_5.jpg","width":150,"height":150},"standard_resolution":{"url":"http:\/\/distilleryimage2.s3.amazonaws.com\/7a76e43273d711e2ad1922000a1cbd31_7.jpg","width":612,"height":612}},"caption":{"created_time":"1360538079","text":"#Snapseed #sky #clouds #sunset #nyc #newyork #manhattan #jj #watertower","from":{"username":"pelletized","profile_picture":"http:\/\/images.instagram.com\/profiles\/profile_203110951_75sq_1361336165.jpg","id":"203110951","full_name":"ed w"},"id":"388544026742022959"},"user_has_liked":false,"id":"388543433986204406_203110951","user":{"username":"pelletized","website":"","profile_picture":"http:\/\/images.instagram.com\/profiles\/profile_203110951_75sq_1361336165.jpg","full_name":"ed w","bio":"","id":"203110951"}},{"attribution":null,"tags":["snowman","urbanart","streetart","newyork","snow","winning","midtown","snapseed","jj","statigram","nyc","webstagram","manhattan"],"type":"image","location":null,"comments":{"count":1,"data":[{"created_time":"1360547932","text":"\ud83d\ude04","from":{"username":"jwheels45","profile_picture":"http:\/\/images.instagram.com\/profiles\/profile_205606283_75sq_1346468328.jpg","id":"205606283","full_name":"jwheels45"},"id":"388626683001757808"}]},"filter":"Hudson","created_time":"1360535790","link":"http:\/\/instagr.am\/p\/VkUUbRjuGY\/","likes":{"count":46,"data":[{"username":"gavrocheconception","profile_picture":"http:\/\/images.instagram.com\/profiles\/profile_289947616_75sq_1358406204.jpg","id":"289947616","full_name":"Gavroche Conception Clothing"},{"username":"samhsnyder","profile_picture":"http:\/\/images.instagram.com\/profiles\/profile_51806160_75sq_1358635400.jpg","id":"51806160","full_name":"Sam H Snyder Design"},{"username":"tonyajoanne","profile_picture":"http:\/\/images.instagram.com\/profiles\/profile_183679620_75sq_1360061713.jpg","id":"183679620","full_name":"tonyajoanne"},{"username":"vkconk","profile_picture":"http:\/\/images.instagram.com\/profiles\/profile_104802054_75sq_1337142042.jpg","id":"104802054","full_name":"Vicki"},{"username":"carbonshowroom","profile_picture":"http:\/\/images.instagram.com\/profiles\/profile_261255558_75sq_1360273899.jpg","id":"261255558","full_name":"Carbon Showroom"},{"username":"ryman03","profile_picture":"http:\/\/images.instagram.com\/profiles\/profile_55264424_75sq_1336927623.jpg","id":"55264424","full_name":"Ryan Byrd"},{"username":"colorvu","profile_picture":"http:\/\/images.instagram.com\/profiles\/profile_2998382_75sq_1357688887.jpg","id":"2998382","full_name":"colorvu"},{"username":"reenie83","profile_picture":"http:\/\/images.instagram.com\/profiles\/profile_193758191_75sq_1345048879.jpg","id":"193758191","full_name":"reenie83"},{"username":"redbenchnyc","profile_picture":"http:\/\/images.instagram.com\/profiles\/profile_261278864_75sq_1358280112.jpg","id":"261278864","full_name":"Red Bench"},{"username":"vincenzd","profile_picture":"http:\/\/images.instagram.com\/profiles\/profile_200282792_75sq_1343512064.jpg","id":"200282792","full_name":"vincenzd"}]},"images":{"low_resolution":{"url":"http:\/\/distilleryimage0.s3.amazonaws.com\/50c02bee73d211e2822f22000a9f09ca_6.jpg","width":306,"height":306},"thumbnail":{"url":"http:\/\/distilleryimage0.s3.amazonaws.com\/50c02bee73d211e2822f22000a9f09ca_5.jpg","width":150,"height":150},"standard_resolution":{"url":"http:\/\/distilleryimage0.s3.amazonaws.com\/50c02bee73d211e2822f22000a9f09ca_7.jpg","width":612,"height":612}},"caption":{"created_time":"1360535891","text":"#Snapseed #statigram #webstagram #jj #snow #snowman #winning #midtown #nyc #newyork #manhattan #streetart #urbanart","from":{"username":"pelletized","profile_picture":"http:\/\/images.instagram.com\/profiles\/profile_203110951_75sq_1361336165.jpg","id":"203110951","full_name":"ed w"},"id":"388525672794873921"},"user_has_liked":false,"id":"388524832466067864_203110951","user":{"username":"pelletized","website":"","profile_picture":"http:\/\/images.instagram.com\/profiles\/profile_203110951_75sq_1361336165.jpg","full_name":"ed w","bio":"","id":"203110951"}},{"attribution":null,"tags":["centralpark","blizzard","newyork","nemo","snow","snapseed","jj","statigram","fun","nyc","webstagram","snowstorm"],"type":"image","location":null,"comments":{"count":0,"data":[]},"filter":"Normal","created_time":"1360465175","link":"http:\/\/instagr.am\/p\/ViNoUwjuM5\/","likes":{"count":55,"data":[{"username":"timo10_87","profile_picture":"http:\/\/images.instagram.com\/profiles\/profile_47910756_75sq_1339244900.jpg","id":"47910756","full_name":"Tim Wheeler"},{"username":"vincenzd","profile_picture":"http:\/\/images.instagram.com\/profiles\/profile_200282792_75sq_1343512064.jpg","id":"200282792","full_name":"vincenzd"},{"username":"csogi","profile_picture":"http:\/\/images.instagram.com\/profiles\/profile_176177962_75sq_1338405495.jpg","id":"176177962","full_name":"Paul Csogi"},{"username":"hatersgonnahateus","profile_picture":"http:\/\/images.instagram.com\/profiles\/profile_182700236_75sq_1361582602.jpg","id":"182700236","full_name":"Christopher Yan"},{"username":"mootskie","profile_picture":"http:\/\/images.instagram.com\/profiles\/profile_22931278_75sq_1361455324.jpg","id":"22931278","full_name":"Jonathan"},{"username":"bicharaca12","profile_picture":"http:\/\/images.instagram.com\/profiles\/profile_185172477_75sq_1361471555.jpg","id":"185172477","full_name":"Steffanie Bichara"},{"username":"jennyr0508","profile_picture":"http:\/\/images.instagram.com\/profiles\/profile_295870840_75sq_1359642695.jpg","id":"295870840","full_name":"Jen Rubino"},{"username":"aakoh","profile_picture":"http:\/\/images.instagram.com\/profiles\/profile_275834634_75sq_1361352550.jpg","id":"275834634","full_name":"Amanda Koh"},{"username":"reblrobot","profile_picture":"http:\/\/images.instagram.com\/profiles\/profile_216413118_75sq_1359955499.jpg","id":"216413118","full_name":"bekah.neas"},{"username":"dianakul","profile_picture":"http:\/\/images.instagram.com\/profiles\/profile_179062751_75sq_1360435983.jpg","id":"179062751","full_name":"Diana Kul"}]},"images":{"low_resolution":{"url":"http:\/\/distilleryimage5.s3.amazonaws.com\/e668f61c732d11e285b022000a9f15de_6.jpg","width":306,"height":306},"thumbnail":{"url":"http:\/\/distilleryimage5.s3.amazonaws.com\/e668f61c732d11e285b022000a9f15de_5.jpg","width":150,"height":150},"standard_resolution":{"url":"http:\/\/distilleryimage5.s3.amazonaws.com\/e668f61c732d11e285b022000a9f15de_7.jpg","width":612,"height":612}},"caption":{"created_time":"1360465283","text":"#fun with filters #snapseed #webstagram #statigram #jj #snow #blizzard #snowstorm #nemo #nyc #newyork #centralpark","from":{"username":"pelletized","profile_picture":"http:\/\/images.instagram.com\/profiles\/profile_203110951_75sq_1361336165.jpg","id":"203110951","full_name":"ed w"},"id":"387933375816459062"},"user_has_liked":false,"id":"387932463580504889_203110951","user":{"username":"pelletized","website":"","profile_picture":"http:\/\/images.instagram.com\/profiles\/profile_203110951_75sq_1361336165.jpg","full_name":"ed w","bio":"","id":"203110951"}},{"attribution":null,"tags":["nyc","stern","snow","nyustern","nyu"],"type":"image","location":{"latitude":40.73105988,"longitude":-73.99702735},"comments":{"count":2,"data":[{"created_time":"1360359277","text":"This is only the beginning \ud83d\ude1c","from":{"username":"jwheels45","profile_picture":"http:\/\/images.instagram.com\/profiles\/profile_205606283_75sq_1346468328.jpg","id":"205606283","full_name":"jwheels45"},"id":"387044127550660611"},{"created_time":"1360371950","text":"Keep us posted! We want to be in on the snow action! \u2744\u26c4","from":{"username":"jmjudson","profile_picture":"http:\/\/images.instagram.com\/profiles\/profile_51754719_75sq_1361554309.jpg","id":"51754719","full_name":"jmjudson"},"id":"387150441043910666"}]},"filter":"X-Pro II","created_time":"1360358135","link":"http:\/\/instagr.am\/p\/VfBd_tjuOV\/","likes":{"count":30,"data":[{"username":"nyustern","profile_picture":"http:\/\/images.instagram.com\/profiles\/profile_32678530_75sq_1333575400.jpg","id":"32678530","full_name":"NYU Stern School of Business"},{"username":"teddy_park","profile_picture":"http:\/\/images.instagram.com\/profiles\/profile_26905669_75sq_1361546578.jpg","id":"26905669","full_name":"!"},{"username":"worldstarhits","profile_picture":"http:\/\/images.instagram.com\/profiles\/profile_203803816_75sq_1357927338.jpg","id":"203803816","full_name":"worldstarhits"},{"username":"blondie81905","profile_picture":"http:\/\/images.instagram.com\/profiles\/profile_254788843_75sq_1353200412.jpg","id":"254788843","full_name":"Erika Toner"},{"username":"samhsnyder","profile_picture":"http:\/\/images.instagram.com\/profiles\/profile_51806160_75sq_1358635400.jpg","id":"51806160","full_name":"Sam H Snyder Design"},{"username":"vincenzd","profile_picture":"http:\/\/images.instagram.com\/profiles\/profile_200282792_75sq_1343512064.jpg","id":"200282792","full_name":"vincenzd"},{"username":"red1elm","profile_picture":"http:\/\/images.instagram.com\/profiles\/profile_254123284_75sq_1353811412.jpg","id":"254123284","full_name":"Red Elm"},{"username":"its_andrean","profile_picture":"http:\/\/images.instagram.com\/profiles\/profile_271857247_75sq_1360506146.jpg","id":"271857247","full_name":"Andrea"},{"username":"carokaramel","profile_picture":"http:\/\/images.instagram.com\/profiles\/profile_8976862_75sq_1359170793.jpg","id":"8976862","full_name":"\u24d2\u24d0\u24e1\u24de\u24db\u24d8\u24dd\u24d0"},{"username":"ticoaa","profile_picture":"http:\/\/images.instagram.com\/profiles\/profile_1081445_75sq_1358741933.jpg","id":"1081445","full_name":"\u24b6\u24c1\u24b7\u24ba\u24c7\u24c9"}]},"images":{"low_resolution":{"url":"http:\/\/distilleryimage9.s3.amazonaws.com\/adf97616723411e2b4ee22000a1fbe6d_6.jpg","width":306,"height":306},"thumbnail":{"url":"http:\/\/distilleryimage9.s3.amazonaws.com\/adf97616723411e2b4ee22000a1fbe6d_5.jpg","width":150,"height":150},"standard_resolution":{"url":"http:\/\/distilleryimage9.s3.amazonaws.com\/adf97616723411e2b4ee22000a1fbe6d_7.jpg","width":612,"height":612}},"caption":{"created_time":"1360358178","text":"#snow #nyc #nyu #stern #nyustern","from":{"username":"pelletized","profile_picture":"http:\/\/images.instagram.com\/profiles\/profile_203110951_75sq_1361336165.jpg","id":"203110951","full_name":"ed w"},"id":"387034910240465538"},"user_has_liked":false,"id":"387034552298562453_203110951","user":{"username":"pelletized","website":"","profile_picture":"http:\/\/images.instagram.com\/profiles\/profile_203110951_75sq_1361336165.jpg","full_name":"ed w","bio":"","id":"203110951"}},{"attribution":null,"tags":["nyc","snow"],"type":"image","location":{"latitude":40.731060028,"longitude":-73.997024536},"comments":{"count":1,"data":[{"created_time":"1360362116","text":"Walk carefully\ud83d\ude04","from":{"username":"nancyw38","profile_picture":"http:\/\/images.instagram.com\/profiles\/anonymousUser.jpg","id":"258976577","full_name":"Nancy"},"id":"387067947506394097"}]},"filter":"Normal","created_time":"1360356282","link":"http:\/\/instagr.am\/p\/Ve97w0juJh\/","likes":{"count":32,"data":[{"username":"teddy_park","profile_picture":"http:\/\/images.instagram.com\/profiles\/profile_26905669_75sq_1361546578.jpg","id":"26905669","full_name":"!"},{"username":"vkconk","profile_picture":"http:\/\/images.instagram.com\/profiles\/profile_104802054_75sq_1337142042.jpg","id":"104802054","full_name":"Vicki"},{"username":"vincenzd","profile_picture":"http:\/\/images.instagram.com\/profiles\/profile_200282792_75sq_1343512064.jpg","id":"200282792","full_name":"vincenzd"},{"username":"aakoh","profile_picture":"http:\/\/images.instagram.com\/profiles\/profile_275834634_75sq_1361352550.jpg","id":"275834634","full_name":"Amanda Koh"},{"username":"blondie81905","profile_picture":"http:\/\/images.instagram.com\/profiles\/profile_254788843_75sq_1353200412.jpg","id":"254788843","full_name":"Erika Toner"},{"username":"mootskie","profile_picture":"http:\/\/images.instagram.com\/profiles\/profile_22931278_75sq_1361455324.jpg","id":"22931278","full_name":"Jonathan"},{"username":"carlagirlnj","profile_picture":"http:\/\/images.instagram.com\/profiles\/profile_202038544_75sq_1343852223.jpg","id":"202038544","full_name":"Carla Jeffrey"},{"username":"jesski4","profile_picture":"http:\/\/images.instagram.com\/profiles\/profile_226514865_75sq_1357414146.jpg","id":"226514865","full_name":"Jessica Krotowski"},{"username":"iviiv","profile_picture":"http:\/\/images.instagram.com\/profiles\/profile_9176341_75sq_1336160705.jpg","id":"9176341","full_name":"Magdalena N"},{"username":"carokaramel","profile_picture":"http:\/\/images.instagram.com\/profiles\/profile_8976862_75sq_1359170793.jpg","id":"8976862","full_name":"\u24d2\u24d0\u24e1\u24de\u24db\u24d8\u24dd\u24d0"}]},"images":{"low_resolution":{"url":"http:\/\/distilleryimage1.s3.amazonaws.com\/5d533246723011e2b9da22000a1faf53_6.jpg","width":306,"height":306},"thumbnail":{"url":"http:\/\/distilleryimage1.s3.amazonaws.com\/5d533246723011e2b9da22000a1faf53_5.jpg","width":150,"height":150},"standard_resolution":{"url":"http:\/\/distilleryimage1.s3.amazonaws.com\/5d533246723011e2b9da22000a1faf53_7.jpg","width":612,"height":612}},"caption":{"created_time":"1360356310","text":"#snow #nyc","from":{"username":"pelletized","profile_picture":"http:\/\/images.instagram.com\/profiles\/profile_203110951_75sq_1361336165.jpg","id":"203110951","full_name":"ed w"},"id":"387019242292043847"},"user_has_liked":false,"id":"387019005708132961_203110951","user":{"username":"pelletized","website":"","profile_picture":"http:\/\/images.instagram.com\/profiles\/profile_203110951_75sq_1361336165.jpg","full_name":"ed w","bio":"","id":"203110951"}},{"attribution":null,"tags":[],"type":"image","location":null,"comments":{"count":8,"data":[{"created_time":"1360272276","text":"Yeah they can do that now","from":{"username":"dparke3","profile_picture":"http:\/\/images.instagram.com\/profiles\/profile_19320349_75sq_1361669785.jpg","id":"19320349","full_name":"Dave Parke III"},"id":"386314316213575949"},{"created_time":"1360274818","text":"Be safe! @pelletized","from":{"username":"tonyajoanne","profile_picture":"http:\/\/images.instagram.com\/profiles\/profile_183679620_75sq_1360061713.jpg","id":"183679620","full_name":"tonyajoanne"},"id":"386335637773410382"},{"created_time":"1360274852","text":"Neat","from":{"username":"jwheels45","profile_picture":"http:\/\/images.instagram.com\/profiles\/profile_205606283_75sq_1346468328.jpg","id":"205606283","full_name":"jwheels45"},"id":"386335924923850834"},{"created_time":"1360276273","text":"Run! \ud83d\ude18 @pelletized","from":{"username":"leighb1987","profile_picture":"http:\/\/images.instagram.com\/profiles\/profile_182523482_75sq_1350610287.jpg","id":"182523482","full_name":"\ud83c\udf34\u2600\ud83c\udf37"},"id":"386347846536716864"},{"created_time":"1360277337","text":"Yes run to bucks county \ud83d\ude01","from":{"username":"jwheels45","profile_picture":"http:\/\/images.instagram.com\/profiles\/profile_205606283_75sq_1346468328.jpg","id":"205606283","full_name":"jwheels45"},"id":"386356771520701368"},{"created_time":"1360286877","text":"Tomorrow snow \u2744 shots await for us ;)","from":{"username":"carokaramel","profile_picture":"http:\/\/images.instagram.com\/profiles\/profile_8976862_75sq_1359170793.jpg","id":"8976862","full_name":"\u24d2\u24d0\u24e1\u24de\u24db\u24d8\u24dd\u24d0"},"id":"386436795661738415"},{"created_time":"1360288428","text":"Run to Maine...oh wait, wrong direction","from":{"username":"nancyw38","profile_picture":"http:\/\/images.instagram.com\/profiles\/anonymousUser.jpg","id":"258976577","full_name":"Nancy"},"id":"386449809790132275"},{"created_time":"1360302896","text":"Stay warm and dry!","from":{"username":"yukinyc","profile_picture":"http:\/\/images.instagram.com\/profiles\/profile_204584848_75sq_1358214638.jpg","id":"204584848","full_name":"yuki"},"id":"386571176254563148"}]},"filter":"Normal","created_time":"1360271151","link":"http:\/\/instagr.am\/p\/Vcbj23juNq\/","likes":{"count":27,"data":[{"username":"edwardcastillo1","profile_picture":"http:\/\/images.instagram.com\/profiles\/profile_10404418_75sq_1357406554.jpg","id":"10404418","full_name":"Edward Castillo"},{"username":"teddy_park","profile_picture":"http:\/\/images.instagram.com\/profiles\/profile_26905669_75sq_1361546578.jpg","id":"26905669","full_name":"!"},{"username":"vkconk","profile_picture":"http:\/\/images.instagram.com\/profiles\/profile_104802054_75sq_1337142042.jpg","id":"104802054","full_name":"Vicki"},{"username":"ellesgold","profile_picture":"http:\/\/images.instagram.com\/profiles\/profile_4527239_75sq_1359865005.jpg","id":"4527239","full_name":"Lori Goldman"},{"username":"vincenzd","profile_picture":"http:\/\/images.instagram.com\/profiles\/profile_200282792_75sq_1343512064.jpg","id":"200282792","full_name":"vincenzd"},{"username":"mootskie","profile_picture":"http:\/\/images.instagram.com\/profiles\/profile_22931278_75sq_1361455324.jpg","id":"22931278","full_name":"Jonathan"},{"username":"keytobeauty","profile_picture":"http:\/\/images.instagram.com\/profiles\/profile_17997715_75sq_1357614372.jpg","id":"17997715","full_name":"Keyanna"},{"username":"m_a_t_t_357","profile_picture":"http:\/\/images.instagram.com\/profiles\/profile_187182935_75sq_1361412142.jpg","id":"187182935","full_name":"Matthew"},{"username":"alyssas90","profile_picture":"http:\/\/images.instagram.com\/profiles\/profile_185851610_75sq_1340506677.jpg","id":"185851610","full_name":"alyssas90"},{"username":"carokaramel","profile_picture":"http:\/\/images.instagram.com\/profiles\/profile_8976862_75sq_1359170793.jpg","id":"8976862","full_name":"\u24d2\u24d0\u24e1\u24de\u24db\u24d8\u24dd\u24d0"}]},"images":{"low_resolution":{"url":"http:\/\/distilleryimage2.s3.amazonaws.com\/279956a6716a11e2ab6822000a1fbc38_6.jpg","width":306,"height":306},"thumbnail":{"url":"http:\/\/distilleryimage2.s3.amazonaws.com\/279956a6716a11e2ab6822000a1fbc38_5.jpg","width":150,"height":150},"standard_resolution":{"url":"http:\/\/distilleryimage2.s3.amazonaws.com\/279956a6716a11e2ab6822000a1fbc38_7.jpg","width":612,"height":612}},"caption":{"created_time":"1360271202","text":"weird, just got this msg on my phone","from":{"username":"pelletized","profile_picture":"http:\/\/images.instagram.com\/profiles\/profile_203110951_75sq_1361336165.jpg","id":"203110951","full_name":"ed w"},"id":"386305303526695848"},"user_has_liked":false,"id":"386304879398675306_203110951","user":{"username":"pelletized","website":"","profile_picture":"http:\/\/images.instagram.com\/profiles\/profile_203110951_75sq_1361336165.jpg","full_name":"ed w","bio":"","id":"203110951"}},{"attribution":null,"tags":["all_shots","river","natural","nature","photo","trees","unitedbytrees","snapseed","pop","jj","statigram","naturelovers","webstagram","picoftheday","photooftheday"],"type":"image","location":null,"comments":{"count":8,"data":[{"created_time":"1360123494","text":"Beautiful photo! Love it \ud83d\udc4c","from":{"username":"stevenromo","profile_picture":"http:\/\/images.instagram.com\/profiles\/profile_12253937_75sq_1361589369.jpg","id":"12253937","full_name":"Steven Romo"},"id":"385066239418884139"},{"created_time":"1360124192","text":"Cool shot!","from":{"username":"micahdawesome","profile_picture":"http:\/\/images.instagram.com\/profiles\/profile_196235522_75sq_1342667491.jpg","id":"196235522","full_name":"Micah Dennis"},"id":"385072094893760736"},{"created_time":"1360124512","text":"@stevenromo @micahdawesome thanks!","from":{"username":"pelletized","profile_picture":"http:\/\/images.instagram.com\/profiles\/profile_203110951_75sq_1361336165.jpg","id":"203110951","full_name":"ed w"},"id":"385074781974618419"},{"created_time":"1360124935","text":"Lovely","from":{"username":"bros_art","profile_picture":"http:\/\/images.instagram.com\/profiles\/profile_240281900_75sq_1359815740.jpg","id":"240281900","full_name":"bros_art"},"id":"385078327830831537"},{"created_time":"1360163508","text":"@bros_art thank you!","from":{"username":"pelletized","profile_picture":"http:\/\/images.instagram.com\/profiles\/profile_203110951_75sq_1361336165.jpg","id":"203110951","full_name":"ed w"},"id":"385401902622237183"},{"created_time":"1360184145","text":"#picoftheday #photooftheday #pop #photo #jj #all_shots","from":{"username":"pelletized","profile_picture":"http:\/\/images.instagram.com\/profiles\/profile_203110951_75sq_1361336165.jpg","id":"203110951","full_name":"ed w"},"id":"385575020573679747"},{"created_time":"1360242061","text":"#unitedbytrees","from":{"username":"pelletized","profile_picture":"http:\/\/images.instagram.com\/profiles\/profile_203110951_75sq_1361336165.jpg","id":"203110951","full_name":"ed w"},"id":"386060847913296090"},{"created_time":"1360253311","text":"It really is one of your best","from":{"username":"jwheels45","profile_picture":"http:\/\/images.instagram.com\/profiles\/profile_205606283_75sq_1346468328.jpg","id":"205606283","full_name":"jwheels45"},"id":"386155219988177303"}]},"filter":"Normal","created_time":"1360123312","link":"http:\/\/instagr.am\/p\/VYBlBFjuPy\/","likes":{"count":67,"data":[{"username":"edwardcastillo1","profile_picture":"http:\/\/images.instagram.com\/profiles\/profile_10404418_75sq_1357406554.jpg","id":"10404418","full_name":"Edward Castillo"},{"username":"teddy_park","profile_picture":"http:\/\/images.instagram.com\/profiles\/profile_26905669_75sq_1361546578.jpg","id":"26905669","full_name":"!"},{"username":"cwehnerfineartimages","profile_picture":"http:\/\/images.instagram.com\/profiles\/profile_4358794_75sq_1361163295.jpg","id":"4358794","full_name":"Chris Wehner"},{"username":"madelaineno","profile_picture":"http:\/\/images.instagram.com\/profiles\/profile_144049079_75sq_1357400340.jpg","id":"144049079","full_name":"madelaineno"},{"username":"mkeahey","profile_picture":"http:\/\/images.instagram.com\/profiles\/profile_246956109_75sq_1353105806.jpg","id":"246956109","full_name":"Mark Keahey"},{"username":"yukinyc","profile_picture":"http:\/\/images.instagram.com\/profiles\/profile_204584848_75sq_1358214638.jpg","id":"204584848","full_name":"yuki"},{"username":"keytobeauty","profile_picture":"http:\/\/images.instagram.com\/profiles\/profile_17997715_75sq_1357614372.jpg","id":"17997715","full_name":"Keyanna"},{"username":"m_a_t_t_357","profile_picture":"http:\/\/images.instagram.com\/profiles\/profile_187182935_75sq_1361412142.jpg","id":"187182935","full_name":"Matthew"},{"username":"its_andrean","profile_picture":"http:\/\/images.instagram.com\/profiles\/profile_271857247_75sq_1360506146.jpg","id":"271857247","full_name":"Andrea"},{"username":"ticoaa","profile_picture":"http:\/\/images.instagram.com\/profiles\/profile_1081445_75sq_1358741933.jpg","id":"1081445","full_name":"\u24b6\u24c1\u24b7\u24ba\u24c7\u24c9"}]},"images":{"low_resolution":{"url":"http:\/\/distilleryimage10.s3.amazonaws.com\/f044593e701111e28d8c22000a1f9ad6_6.jpg","width":306,"height":306},"thumbnail":{"url":"http:\/\/distilleryimage10.s3.amazonaws.com\/f044593e701111e28d8c22000a1f9ad6_5.jpg","width":150,"height":150},"standard_resolution":{"url":"http:\/\/distilleryimage10.s3.amazonaws.com\/f044593e701111e28d8c22000a1f9ad6_7.jpg","width":612,"height":612}},"caption":{"created_time":"1360123356","text":"#snapseed #webstagram #statigram #trees #naturelovers #nature #natural #river","from":{"username":"pelletized","profile_picture":"http:\/\/images.instagram.com\/profiles\/profile_203110951_75sq_1361336165.jpg","id":"203110951","full_name":"ed w"},"id":"385065084794101774"},"user_has_liked":false,"id":"385064709974320114_203110951","user":{"username":"pelletized","website":"","profile_picture":"http:\/\/images.instagram.com\/profiles\/profile_203110951_75sq_1361336165.jpg","full_name":"ed w","bio":"","id":"203110951"}},{"attribution":null,"tags":[],"type":"image","location":null,"comments":{"count":8,"data":[{"created_time":"1360013012","text":"Awesome!","from":{"username":"jennyr0508","profile_picture":"http:\/\/images.instagram.com\/profiles\/profile_295870840_75sq_1359642695.jpg","id":"295870840","full_name":"Jen Rubino"},"id":"384139452811763987"},{"created_time":"1360013068","text":"Where is the studio for that?","from":{"username":"dparke3","profile_picture":"http:\/\/images.instagram.com\/profiles\/profile_19320349_75sq_1361669785.jpg","id":"19320349","full_name":"Dave Parke III"},"id":"384139919486804259"},{"created_time":"1360014677","text":"@dparke3 52nd \u002611th","from":{"username":"pelletized","profile_picture":"http:\/\/images.instagram.com\/profiles\/profile_203110951_75sq_1361336165.jpg","id":"203110951","full_name":"ed w"},"id":"384153416278926039"},{"created_time":"1360017256","text":"Don't forget ur John 3:16 sign! Lol","from":{"username":"mattgalletta","profile_picture":"http:\/\/images.instagram.com\/profiles\/profile_40796655_75sq_1361328174.jpg","id":"40796655","full_name":"Matthew Galletta"},"id":"384175052705161682"},{"created_time":"1360022406","text":"Boo, just because you have ticket in hand doesn't mean you get in. Had a great time hanging out on the corner for an hour in 20 degree weather =\\","from":{"username":"pelletized","profile_picture":"http:\/\/images.instagram.com\/profiles\/profile_203110951_75sq_1361336165.jpg","id":"203110951","full_name":"ed w"},"id":"384218249900777585"},{"created_time":"1360023080","text":"Maybe next time \ud83d\ude01","from":{"username":"jwheels45","profile_picture":"http:\/\/images.instagram.com\/profiles\/profile_205606283_75sq_1346468328.jpg","id":"205606283","full_name":"jwheels45"},"id":"384223901549257063"},{"created_time":"1360025325","text":"That's ridiculous @pelletized","from":{"username":"tonyajoanne","profile_picture":"http:\/\/images.instagram.com\/profiles\/profile_183679620_75sq_1360061713.jpg","id":"183679620","full_name":"tonyajoanne"},"id":"384242736121701359"},{"created_time":"1360029217","text":"That stinks! \ud83d\ude22","from":{"username":"leighb1987","profile_picture":"http:\/\/images.instagram.com\/profiles\/profile_182523482_75sq_1350610287.jpg","id":"182523482","full_name":"\ud83c\udf34\u2600\ud83c\udf37"},"id":"384275385464840588"}]},"filter":"Rise","created_time":"1360012075","link":"http:\/\/instagr.am\/p\/VUtaRAjuJ8\/","likes":{"count":27,"data":[{"username":"matuporreca","profile_picture":"http:\/\/images.instagram.com\/profiles\/profile_183341377_75sq_1354749851.jpg","id":"183341377","full_name":"matuporreca"},{"username":"edwardcastillo1","profile_picture":"http:\/\/images.instagram.com\/profiles\/profile_10404418_75sq_1357406554.jpg","id":"10404418","full_name":"Edward Castillo"},{"username":"teddy_park","profile_picture":"http:\/\/images.instagram.com\/profiles\/profile_26905669_75sq_1361546578.jpg","id":"26905669","full_name":"!"},{"username":"ryman03","profile_picture":"http:\/\/images.instagram.com\/profiles\/profile_55264424_75sq_1336927623.jpg","id":"55264424","full_name":"Ryan Byrd"},{"username":"blondie81905","profile_picture":"http:\/\/images.instagram.com\/profiles\/profile_254788843_75sq_1353200412.jpg","id":"254788843","full_name":"Erika Toner"},{"username":"keytobeauty","profile_picture":"http:\/\/images.instagram.com\/profiles\/profile_17997715_75sq_1357614372.jpg","id":"17997715","full_name":"Keyanna"},{"username":"m_a_t_t_357","profile_picture":"http:\/\/images.instagram.com\/profiles\/profile_187182935_75sq_1361412142.jpg","id":"187182935","full_name":"Matthew"},{"username":"leighb1987","profile_picture":"http:\/\/images.instagram.com\/profiles\/profile_182523482_75sq_1350610287.jpg","id":"182523482","full_name":"\ud83c\udf34\u2600\ud83c\udf37"},{"username":"kimmyks","profile_picture":"http:\/\/images.instagram.com\/profiles\/profile_5650458_75sq_1352598183.jpg","id":"5650458","full_name":"kimmyks"},{"username":"yasiruae","profile_picture":"http:\/\/images.instagram.com\/profiles\/profile_6021630_75sq_1359533974.jpg","id":"6021630","full_name":"Yasir Albehzad"}]},"images":{"low_resolution":{"url":"http:\/\/distilleryimage0.s3.amazonaws.com\/f1c42e466f0e11e2a7d422000a9e0846_6.jpg","width":306,"height":306},"thumbnail":{"url":"http:\/\/distilleryimage0.s3.amazonaws.com\/f1c42e466f0e11e2a7d422000a9e0846_5.jpg","width":150,"height":150},"standard_resolution":{"url":"http:\/\/distilleryimage0.s3.amazonaws.com\/f1c42e466f0e11e2a7d422000a9e0846_7.jpg","width":612,"height":612}},"caption":{"created_time":"1360012118","text":"Look for me tonight!","from":{"username":"pelletized","profile_picture":"http:\/\/images.instagram.com\/profiles\/profile_203110951_75sq_1361336165.jpg","id":"203110951","full_name":"ed w"},"id":"384131945972293644"},"user_has_liked":false,"id":"384131585295704700_203110951","user":{"username":"pelletized","website":"","profile_picture":"http:\/\/images.instagram.com\/profiles\/profile_203110951_75sq_1361336165.jpg","full_name":"ed w","bio":"","id":"203110951"}},{"attribution":null,"tags":["art","streetart","instahub","newyork","awesome","park","lol","jj","love","girl","worldsfair","best","queens","newyorkcity","like","cow","daily","wow","bestagram","all_shots","nexus4","snapseed","bestoftheday","iloveny","statigram","nyc","webstagram","picoftheday","photooftheday"],"type":"image","location":null,"comments":{"count":4,"data":[{"created_time":"1359954050","text":"#jj #queens #nyc #newyork #newyorkcity #iloveny #instahub","from":{"username":"pelletized","profile_picture":"http:\/\/images.instagram.com\/profiles\/profile_203110951_75sq_1361336165.jpg","id":"203110951","full_name":"ed w"},"id":"383644838891806831"},{"created_time":"1359954086","text":"#bestagram #bestoftheday #best #picoftheday #photooftheday #park","from":{"username":"pelletized","profile_picture":"http:\/\/images.instagram.com\/profiles\/profile_203110951_75sq_1361336165.jpg","id":"203110951","full_name":"ed w"},"id":"383645143700267136"},{"created_time":"1359954209","text":"#art #all_shots #awesome #like #love #lol","from":{"username":"pelletized","profile_picture":"http:\/\/images.instagram.com\/profiles\/profile_203110951_75sq_1361336165.jpg","id":"203110951","full_name":"ed w"},"id":"383646175088009375"},{"created_time":"1359954953","text":"#girl #nexus4 #daily","from":{"username":"pelletized","profile_picture":"http:\/\/images.instagram.com\/profiles\/profile_203110951_75sq_1361336165.jpg","id":"203110951","full_name":"ed w"},"id":"383652411976114534"}]},"filter":"Normal","created_time":"1359953849","link":"http:\/\/instagr.am\/p\/VS-WnlDuHE\/","likes":{"count":65,"data":[{"username":"matuporreca","profile_picture":"http:\/\/images.instagram.com\/profiles\/profile_183341377_75sq_1354749851.jpg","id":"183341377","full_name":"matuporreca"},{"username":"edwardcastillo1","profile_picture":"http:\/\/images.instagram.com\/profiles\/profile_10404418_75sq_1357406554.jpg","id":"10404418","full_name":"Edward Castillo"},{"username":"jwheels45","profile_picture":"http:\/\/images.instagram.com\/profiles\/profile_205606283_75sq_1346468328.jpg","id":"205606283","full_name":"jwheels45"},{"username":"tonyajoanne","profile_picture":"http:\/\/images.instagram.com\/profiles\/profile_183679620_75sq_1360061713.jpg","id":"183679620","full_name":"tonyajoanne"},{"username":"doughboy3333","profile_picture":"http:\/\/images.instagram.com\/profiles\/profile_23591237_75sq_1357419859.jpg","id":"23591237","full_name":"\u24d9\u24d0\u24da\u24d4"},{"username":"ryman03","profile_picture":"http:\/\/images.instagram.com\/profiles\/profile_55264424_75sq_1336927623.jpg","id":"55264424","full_name":"Ryan Byrd"},{"username":"blondie81905","profile_picture":"http:\/\/images.instagram.com\/profiles\/profile_254788843_75sq_1353200412.jpg","id":"254788843","full_name":"Erika Toner"},{"username":"guriboy007","profile_picture":"http:\/\/images.instagram.com\/profiles\/profile_686354_75sq_1357375122.jpg","id":"686354","full_name":"Cesar A Farias"},{"username":"m_a_t_t_357","profile_picture":"http:\/\/images.instagram.com\/profiles\/profile_187182935_75sq_1361412142.jpg","id":"187182935","full_name":"Matthew"},{"username":"erikalokay","profile_picture":"http:\/\/images.instagram.com\/profiles\/profile_52758554_75sq_1352471735.jpg","id":"52758554","full_name":"erikalokay"}]},"images":{"low_resolution":{"url":"http:\/\/distilleryimage4.s3.amazonaws.com\/6074222a6e8711e2902022000a1ddbd3_6.jpg","width":306,"height":306},"thumbnail":{"url":"http:\/\/distilleryimage4.s3.amazonaws.com\/6074222a6e8711e2902022000a1ddbd3_5.jpg","width":150,"height":150},"standard_resolution":{"url":"http:\/\/distilleryimage4.s3.amazonaws.com\/6074222a6e8711e2902022000a1ddbd3_7.jpg","width":612,"height":612}},"caption":{"created_time":"1359953907","text":"#Snapseed #webstagram #statigram #streetart #cow #worldsfair #wow","from":{"username":"pelletized","profile_picture":"http:\/\/images.instagram.com\/profiles\/profile_203110951_75sq_1361336165.jpg","id":"203110951","full_name":"ed w"},"id":"383643639488634951"},"user_has_liked":false,"id":"383643151489753540_203110951","user":{"username":"pelletized","website":"","profile_picture":"http:\/\/images.instagram.com\/profiles\/profile_203110951_75sq_1361336165.jpg","full_name":"ed w","bio":"","id":"203110951"}},{"attribution":null,"tags":["love","instahub","cars","instapic","instalike","graffiti","instaphoto","jj","instalove","best","like","tx","wow","bestagram","sky","lol","instasky","snapseed","bestoftheday","fog","statigram","webstagram","picoftheday","texas","photooftheday"],"type":"image","location":null,"comments":{"count":8,"data":[{"created_time":"1359780829","text":"#tx #wow #lol #fog #like #love #instalike #instalove #instahub #instasky #sky","from":{"username":"pelletized","profile_picture":"http:\/\/images.instagram.com\/profiles\/profile_203110951_75sq_1361336165.jpg","id":"203110951","full_name":"ed w"},"id":"382191754558759270"},{"created_time":"1359782145","text":"#bestagram #bestoftheday #best #picoftheday #photooftheday #instapic #instaphoto","from":{"username":"pelletized","profile_picture":"http:\/\/images.instagram.com\/profiles\/profile_203110951_75sq_1361336165.jpg","id":"203110951","full_name":"ed w"},"id":"382202797271999069"},{"created_time":"1359782177","text":"#texas #jj","from":{"username":"pelletized","profile_picture":"http:\/\/images.instagram.com\/profiles\/profile_203110951_75sq_1361336165.jpg","id":"203110951","full_name":"ed w"},"id":"382203064776319586"},{"created_time":"1359835530","text":"Where is this","from":{"username":"jwheels45","profile_picture":"http:\/\/images.instagram.com\/profiles\/profile_205606283_75sq_1346468328.jpg","id":"205606283","full_name":"jwheels45"},"id":"382650623076524302"},{"created_time":"1359835556","text":"Neat\ud83d\ude03","from":{"username":"jwheels45","profile_picture":"http:\/\/images.instagram.com\/profiles\/profile_205606283_75sq_1346468328.jpg","id":"205606283","full_name":"jwheels45"},"id":"382650843319427355"},{"created_time":"1360163571","text":"@jwheels45 north texas","from":{"username":"pelletized","profile_picture":"http:\/\/images.instagram.com\/profiles\/profile_203110951_75sq_1361336165.jpg","id":"203110951","full_name":"ed w"},"id":"385402426490806788"},{"created_time":"1360243826","text":"Yes, that's Texas, seen that, good shot if it!!","from":{"username":"sharfull","profile_picture":"http:\/\/images.instagram.com\/profiles\/profile_277647311_75sq_1361804168.jpg","id":"277647311","full_name":"Sharon"},"id":"386075654192292386"},{"created_time":"1360707602","text":"@sharfull thanks!","from":{"username":"pelletized","profile_picture":"http:\/\/images.instagram.com\/profiles\/profile_203110951_75sq_1361336165.jpg","id":"203110951","full_name":"ed w"},"id":"389966090002686357"}]},"filter":"Normal","created_time":"1359780695","link":"http:\/\/instagr.am\/p\/VN0Fu7DuEb\/","likes":{"count":67,"data":[{"username":"ticoaa","profile_picture":"http:\/\/images.instagram.com\/profiles\/profile_1081445_75sq_1358741933.jpg","id":"1081445","full_name":"\u24b6\u24c1\u24b7\u24ba\u24c7\u24c9"},{"username":"vkconk","profile_picture":"http:\/\/images.instagram.com\/profiles\/profile_104802054_75sq_1337142042.jpg","id":"104802054","full_name":"Vicki"},{"username":"worldstarhits","profile_picture":"http:\/\/images.instagram.com\/profiles\/profile_203803816_75sq_1357927338.jpg","id":"203803816","full_name":"worldstarhits"},{"username":"sharfull","profile_picture":"http:\/\/images.instagram.com\/profiles\/profile_277647311_75sq_1357508711.jpg","id":"277647311","full_name":"Sharon Sanders"},{"username":"bobbyk_03","profile_picture":"http:\/\/images.instagram.com\/profiles\/profile_35166800_75sq_1361134195.jpg","id":"35166800","full_name":"R\ud83d\ude31BERT \u303dARE\u26a1"},{"username":"skyviewers","profile_picture":"http:\/\/images.instagram.com\/profiles\/profile_249066184_75sq_1361482412.jpg","id":"249066184","full_name":"#skyviewers"},{"username":"red1elm","profile_picture":"http:\/\/images.instagram.com\/profiles\/profile_254123284_75sq_1353811412.jpg","id":"254123284","full_name":"Red Elm"},{"username":"roeysdomi","profile_picture":"http:\/\/images.instagram.com\/profiles\/profile_21783899_75sq_1361480679.jpg","id":"21783899","full_name":"Roey Sdomi"},{"username":"carokaramel","profile_picture":"http:\/\/images.instagram.com\/profiles\/profile_8976862_75sq_1359170793.jpg","id":"8976862","full_name":"\u24d2\u24d0\u24e1\u24de\u24db\u24d8\u24dd\u24d0"},{"username":"instarekiem","profile_picture":"http:\/\/images.instagram.com\/profiles\/profile_207134271_75sq_1359150445.jpg","id":"207134271","full_name":"#\u20e3instaRekiem \ud83d\udc48"}]},"images":{"low_resolution":{"url":"http:\/\/distilleryimage3.s3.amazonaws.com\/39022e246cf411e2890222000a1fb0b2_6.jpg","width":306,"height":306},"thumbnail":{"url":"http:\/\/distilleryimage3.s3.amazonaws.com\/39022e246cf411e2890222000a1fb0b2_5.jpg","width":150,"height":150},"standard_resolution":{"url":"http:\/\/distilleryimage3.s3.amazonaws.com\/39022e246cf411e2890222000a1fb0b2_7.jpg","width":612,"height":612}},"caption":{"created_time":"1359780739","text":"#Snapseed #webstagram #statigram #cars #graffiti","from":{"username":"pelletized","profile_picture":"http:\/\/images.instagram.com\/profiles\/profile_203110951_75sq_1361336165.jpg","id":"203110951","full_name":"ed w"},"id":"382191002369057096"},"user_has_liked":false,"id":"382190635795276059_203110951","user":{"username":"pelletized","website":"","profile_picture":"http:\/\/images.instagram.com\/profiles\/profile_203110951_75sq_1361336165.jpg","full_name":"ed w","bio":"","id":"203110951"}}]}